LICENSE.md
README.md
orbit_component_dbshell/__init__.py
orbit_component_dbshell/plugin.py
orbit_component_dbshell-1.0.8.dist-info/LICENSE.md
orbit_component_dbshell-1.0.8.dist-info/METADATA
orbit_component_dbshell-1.0.8.dist-info/WHEEL
orbit_component_dbshell-1.0.8.dist-info/RECORD
